net_work/__init__.py
net_work/__main__.py
net_work/client.py
net_work/server.py
net_work/structs.py
j_net_work-0.0.3.dist-info/METADATA
j_net_work-0.0.3.dist-info/WHEEL
j_net_work-0.0.3.dist-info/top_level.txt
j_net_work-0.0.3.dist-info/RECORD
